{
  "_class": "symbolInstance",
  "booleanOperation": -1,
  "clippingMaskMode": 0,
  "do_objectID": "775B1FF0-D656-4AF4-834D-C5E3C79BB6BA",
  "exportOptions": {
    "_class": "exportOptions",
    "do_objectID": "E3574536-069A-4954-87D1-AAA3E5505156",
    "exportFormats": [
    ],
    "includedLayerIds": [
    ],
    "layerOptions": 0,
    "shouldTrim": false
  },
  "frame": {
    "_class": "rect",
    "constrainProportions": false,
    "do_objectID": "1BF8545A-587F-4E20-95C3-5F10FCBA59B5",
    "height": 17,
    "width": 20,
    "x": 460,
    "y": 36
  },
  "hasClippingMask": false,
  "horizontalSpacing": 0,
  "isFixedToViewport": false,
  "isFlippedHorizontal": false,
  "isFlippedVertical": false,
  "isLocked": false,
  "isVisible": true,
  "layerListExpandedType": 0,
  "name": "Expand Arrow",
  "nameIsFixed": false,
  "overrideValues": [
  ],
  "resizingConstraint": 63,
  "resizingType": 0,
  "rotation": 0,
  "scale": 1,
  "shouldBreakMaskChain": false,
  "style": {
    "_class": "style",
    "do_objectID": "C6810BE2-8ECA-4076-9877-58CA0659B4E2",
    "endMarkerType": 0,
    "miterLimit": 10,
    "startMarkerType": 0,
    "windingRule": 1
  },
  "symbolID": "4F285294-2B72-49BF-B14A-7C3E0B850739",
  "verticalSpacing": 0
}