{
  "_class": "shapeGroup",
  "booleanOperation": 1,
  "clippingMaskMode": 0,
  "do_objectID": "A753B0CB-F824-48C7-A575-EE8799837FFD",
  "exportOptions": {
    "_class": "exportOptions",
    "do_objectID": "F4701635-84CA-4872-BAEF-02F592CBC6E6",
    "exportFormats": [
    ],
    "includedLayerIds": [
    ],
    "layerOptions": 0,
    "shouldTrim": false
  },
  "frame": {
    "_class": "rect",
    "constrainProportions": false,
    "do_objectID": "16666B04-9AC6-49FC-8194-88A86381B3C0",
    "height": 193,
    "width": 193,
    "x": -97,
    "y": -0.001177515975996357
  },
  "groupLayout": {
    "_class": "MSImmutableFreeformGroupLayout",
    "do_objectID": "DA1EEA33-24BF-47A7-AD2E-32F654E9A8F1"
  },
  "hasClickThrough": false,
  "hasClippingMask": false,
  "isFixedToViewport": false,
  "isFlippedHorizontal": false,
  "isFlippedVertical": false,
  "isLocked": false,
  "isVisible": true,
  "layerListExpandedType": 0,
  "layers": [
    {
      "class": "oval",
      "id": "49860BB4-33F3-4DC9-BBFA-5875612F8622"
    },
    {
      "class": "oval",
      "id": "38CE786E-A11F-4D5F-AD48-0811E4C41CCE"
    }
  ],
  "name": "Combined Shape",
  "nameIsFixed": false,
  "resizingConstraint": 63,
  "resizingType": 0,
  "rotation": 0,
  "shouldBreakMaskChain": false,
  "style": {
    "_class": "style",
    "borders": [
      {
        "_class": "border",
        "color": {
          "_class": "color",
          "alpha": 1,
          "blue": 0.592,
          "green": 0.592,
          "red": 0.592
        },
        "fillType": 0,
        "isEnabled": false,
        "position": 0,
        "thickness": 1
      }
    ],
    "do_objectID": "1DEB229C-1D41-4F0E-9D22-3342CF3CEBE2",
    "endMarkerType": 0,
    "fills": [
      {
        "_class": "fill",
        "color": {
          "_class": "color",
          "alpha": 1,
          "blue": 0.847,
          "green": 0.847,
          "red": 0.847
        },
        "fillType": 0,
        "isEnabled": true,
        "noiseIndex": 0,
        "noiseIntensity": 0,
        "patternFillType": 1,
        "patternTileScale": 1
      }
    ],
    "miterLimit": 10,
    "startMarkerType": 0,
    "windingRule": 1
  },
  "windingRule": 1
}