{
  "_class": "shapeGroup",
  "booleanOperation": 1,
  "clippingMaskMode": 0,
  "do_objectID": "F7E4587E-7DC6-4A47-B4D8-BB64CE7C1411",
  "exportOptions": {
    "_class": "exportOptions",
    "do_objectID": "61904D0E-3E5C-451C-8454-FF22749AD633",
    "exportFormats": [
    ],
    "includedLayerIds": [
    ],
    "layerOptions": 0,
    "shouldTrim": false
  },
  "frame": {
    "_class": "rect",
    "constrainProportions": false,
    "do_objectID": "6D43D540-9DAE-42A9-958C-DCCC10DB71D0",
    "height": 193,
    "width": 193,
    "x": -97,
    "y": -0.001177515975996357
  },
  "groupLayout": {
    "_class": "MSImmutableFreeformGroupLayout",
    "do_objectID": "FE7634D2-6393-482C-BAAE-24BC9EDF903B"
  },
  "hasClickThrough": false,
  "hasClippingMask": false,
  "isFixedToViewport": false,
  "isFlippedHorizontal": false,
  "isFlippedVertical": false,
  "isLocked": false,
  "isVisible": true,
  "layerListExpandedType": 0,
  "layers": [
    {
      "class": "oval",
      "id": "6ABC04AD-FAF8-4251-8372-6C0F36AEAC48"
    },
    {
      "class": "oval",
      "id": "B950ACF0-264A-456F-A769-8B5C2A502D36"
    }
  ],
  "name": "Combined Shape",
  "nameIsFixed": false,
  "resizingConstraint": 63,
  "resizingType": 0,
  "rotation": 0,
  "shouldBreakMaskChain": false,
  "style": {
    "_class": "style",
    "borders": [
      {
        "_class": "border",
        "color": {
          "_class": "color",
          "alpha": 1,
          "blue": 0.592,
          "green": 0.592,
          "red": 0.592
        },
        "fillType": 0,
        "isEnabled": false,
        "position": 0,
        "thickness": 1
      }
    ],
    "do_objectID": "3F5F2A13-A0B1-4637-86CA-DFE84F7D1167",
    "endMarkerType": 0,
    "fills": [
      {
        "_class": "fill",
        "color": {
          "_class": "color",
          "alpha": 1,
          "blue": 0.847,
          "green": 0.847,
          "red": 0.847
        },
        "fillType": 0,
        "isEnabled": true,
        "noiseIndex": 0,
        "noiseIntensity": 0,
        "patternFillType": 1,
        "patternTileScale": 1
      }
    ],
    "miterLimit": 10,
    "startMarkerType": 0,
    "windingRule": 1
  },
  "windingRule": 1
}