{
  "_class": "group",
  "booleanOperation": -1,
  "clippingMaskMode": 0,
  "do_objectID": "221D5CCD-F130-4280-A43D-0EB4A8601E94",
  "exportOptions": {
    "_class": "exportOptions",
    "do_objectID": "5E9F620E-881E-445B-A078-4C339B925E02",
    "exportFormats": [
    ],
    "includedLayerIds": [
    ],
    "layerOptions": 0,
    "shouldTrim": false
  },
  "frame": {
    "_class": "rect",
    "constrainProportions": false,
    "do_objectID": "8175ADB2-0222-451D-997B-45DCBB539780",
    "height": 128,
    "width": 1440,
    "x": 0,
    "y": 0
  },
  "groupLayout": {
    "_class": "MSImmutableFreeformGroupLayout",
    "do_objectID": "E9E25CDB-D6DF-4B0F-909B-3C2A5E9B2237"
  },
  "hasClickThrough": false,
  "hasClippingMask": false,
  "isFixedToViewport": false,
  "isFlippedHorizontal": false,
  "isFlippedVertical": false,
  "isLocked": false,
  "isVisible": true,
  "layerListExpandedType": 0,
  "layers": [
    {
      "class": "symbolInstance",
      "id": "0A181244-C9F5-4BB7-8925-E76C574D6E33"
    },
    {
      "class": "symbolInstance",
      "id": "77E04A81-B4B8-405B-A2AF-2ADB92391DD5"
    },
    {
      "class": "symbolInstance",
      "id": "7A71C79E-F772-4F58-8EA2-9E89031ADCD3"
    },
    {
      "class": "text",
      "id": "42D04A72-A98A-46EC-B8F0-8C75E7100EF4"
    },
    {
      "class": "text",
      "id": "71ABD4D9-2AC0-4AD3-BC91-511E384A5621"
    },
    {
      "class": "text",
      "id": "720AF68A-D0FF-483D-8853-5665C551C515"
    }
  ],
  "name": "Navbar Copy",
  "nameIsFixed": true,
  "resizingConstraint": 63,
  "resizingType": 0,
  "rotation": 0,
  "shouldBreakMaskChain": false,
  "style": {
    "_class": "style",
    "do_objectID": "1DEF13E6-E72E-49F0-8399-F32C6065BB2B",
    "endMarkerType": 0,
    "miterLimit": 10,
    "startMarkerType": 0,
    "windingRule": 1
  }
}