{
  "_class": "shapeGroup",
  "booleanOperation": 1,
  "clippingMaskMode": 0,
  "do_objectID": "1A3E6698-1B27-4DC9-AF3D-D383918EAFA0",
  "exportOptions": {
    "_class": "exportOptions",
    "do_objectID": "2D2C02D3-48FD-46B2-94EF-F4D3324A86A2",
    "exportFormats": [
    ],
    "includedLayerIds": [
    ],
    "layerOptions": 0,
    "shouldTrim": false
  },
  "frame": {
    "_class": "rect",
    "constrainProportions": false,
    "do_objectID": "23EEE825-C821-4078-97D2-F974B3B2F375",
    "height": 193,
    "width": 193,
    "x": -97,
    "y": -0.001177515975996357
  },
  "groupLayout": {
    "_class": "MSImmutableFreeformGroupLayout",
    "do_objectID": "636F2EF2-56D4-4C70-A9C3-773262AD854C"
  },
  "hasClickThrough": false,
  "hasClippingMask": false,
  "isFixedToViewport": false,
  "isFlippedHorizontal": false,
  "isFlippedVertical": false,
  "isLocked": false,
  "isVisible": true,
  "layerListExpandedType": 0,
  "layers": [
    {
      "class": "oval",
      "id": "9BFC8CAE-250A-4B99-A4F3-B0BB2007DBB9"
    },
    {
      "class": "oval",
      "id": "1B61953F-7BBE-485B-84F1-F45A5A646F25"
    }
  ],
  "name": "Combined Shape",
  "nameIsFixed": false,
  "resizingConstraint": 63,
  "resizingType": 0,
  "rotation": 0,
  "shouldBreakMaskChain": false,
  "style": {
    "_class": "style",
    "borders": [
      {
        "_class": "border",
        "color": {
          "_class": "color",
          "alpha": 1,
          "blue": 0.592,
          "green": 0.592,
          "red": 0.592
        },
        "fillType": 0,
        "isEnabled": false,
        "position": 0,
        "thickness": 1
      }
    ],
    "do_objectID": "4508155F-1641-43CB-83D5-ABB2FDE1B09B",
    "endMarkerType": 0,
    "fills": [
      {
        "_class": "fill",
        "color": {
          "_class": "color",
          "alpha": 1,
          "blue": 0.847,
          "green": 0.847,
          "red": 0.847
        },
        "fillType": 0,
        "isEnabled": true,
        "noiseIndex": 0,
        "noiseIntensity": 0,
        "patternFillType": 1,
        "patternTileScale": 1
      }
    ],
    "miterLimit": 10,
    "startMarkerType": 0,
    "windingRule": 1
  },
  "windingRule": 1
}