{
  "_class": "symbolInstance",
  "booleanOperation": -1,
  "clippingMaskMode": 0,
  "do_objectID": "EE94C3DA-681A-4894-A54C-09F25854AF6C",
  "exportOptions": {
    "_class": "exportOptions",
    "do_objectID": "E69B1EC4-E669-4517-8E5B-E904416C9B3B",
    "exportFormats": [
    ],
    "includedLayerIds": [
    ],
    "layerOptions": 0,
    "shouldTrim": false
  },
  "frame": {
    "_class": "rect",
    "constrainProportions": false,
    "do_objectID": "A36CA3F1-BAB2-4FC9-A941-5AFDB692D5AE",
    "height": 17,
    "width": 20,
    "x": 460,
    "y": 36
  },
  "hasClippingMask": false,
  "horizontalSpacing": 0,
  "isFixedToViewport": false,
  "isFlippedHorizontal": false,
  "isFlippedVertical": false,
  "isLocked": false,
  "isVisible": true,
  "layerListExpandedType": 0,
  "name": "Expand Arrow Copy",
  "nameIsFixed": false,
  "overrideValues": [
  ],
  "resizingConstraint": 63,
  "resizingType": 0,
  "rotation": 0,
  "scale": 1,
  "shouldBreakMaskChain": false,
  "style": {
    "_class": "style",
    "do_objectID": "A194D97B-0365-4F82-82BF-DE593BCD8D1C",
    "endMarkerType": 0,
    "miterLimit": 10,
    "startMarkerType": 0,
    "windingRule": 1
  },
  "symbolID": "4F285294-2B72-49BF-B14A-7C3E0B850739",
  "verticalSpacing": 0
}