{
  "_class": "group",
  "booleanOperation": -1,
  "clippingMaskMode": 0,
  "do_objectID": "3D771E3D-2BEA-41C7-A410-7F5DD7F669FE",
  "exportOptions": {
    "_class": "exportOptions",
    "do_objectID": "9B45E6B7-B247-46A5-88F1-83FEA9F8EE82",
    "exportFormats": [
    ],
    "includedLayerIds": [
    ],
    "layerOptions": 0,
    "shouldTrim": false
  },
  "frame": {
    "_class": "rect",
    "constrainProportions": false,
    "do_objectID": "022923F5-A7B2-434A-9446-E19C0AE17FBB",
    "height": 47,
    "width": 59,
    "x": 0,
    "y": 0
  },
  "groupLayout": {
    "_class": "MSImmutableFreeformGroupLayout",
    "do_objectID": "880C914E-52DE-4A34-9A18-15116889BAC9"
  },
  "hasClickThrough": false,
  "hasClippingMask": false,
  "isFixedToViewport": false,
  "isFlippedHorizontal": false,
  "isFlippedVertical": false,
  "isLocked": false,
  "isVisible": true,
  "layerListExpandedType": 0,
  "layers": [
    {
      "class": "rectangle",
      "id": "101B0981-3F2B-4CC2-9E76-C76E211F1C46"
    },
    {
      "class": "shapePath",
      "id": "B246C8CD-92EA-47BA-888D-F4338163208D"
    }
  ],
  "name": "Dropdown",
  "nameIsFixed": true,
  "resizingConstraint": 63,
  "resizingType": 0,
  "rotation": 0,
  "shouldBreakMaskChain": false,
  "style": {
    "_class": "style",
    "do_objectID": "F0C9963A-846A-4A5D-A0C7-EB263B67EAFA",
    "endMarkerType": 0,
    "miterLimit": 10,
    "startMarkerType": 0,
    "windingRule": 1
  }
}